{
  "sd_selected_model": "waiIllustriousSDXL_v160.safetensors",
  "sd_selected_sampler": "DPM++ 2M SDE",
  "sd_steps_value": 30,
  "sd_cfg_scale_value": 6.0,
  "sd_upscaling_enabled": false,
  "sd_upscaling_size": 1.75,
  "sd_selected_upscaler": "SwinIR_4x",
  "sd_width_value": "768",
  "sd_height_value": "1152",
  "sd_adetailer_enabled": true,
  "sd_selected_adetailer": "face_yolov8n.pt",
  "sd_selected_prompt": "WAIFU",
  "sd_selected_scheduler": "karras",
  "sd_global_positive_prepend": " masterpiece, best quality, anime style",
  "sd_global_negative_prepend": " bad quality, worst quality, worst detail, closed eyes,censored,low quality, lowres, jpeg artifacts, bad anatomy, bad hands, watermark",
  "sd_img2img_enabled": false,
  "sd_denoising_strength": 0.5,
  "sd_json_correction": false,
  "sd_adetailer_model": null,
  "sd_latent_enabled": false,
  "sd_noise_strength": 25.0,
  "sd_noise_type": "add"
}